{
  "indexes": [
    {
      "collectionGroup": "veiculos",
      "queryScope": "COLLECTION",
      "fields": [
        { "fieldPath": "situacao", "order": "ASCENDING" },
        { "fieldPath": "placa", "order": "ASCENDING" }
      ]
    },
    {
      "collectionGroup": "veiculos",
      "queryScope": "COLLECTION",
      "fields": [
        { "fieldPath": "clienteCpf", "order": "ASCENDING" },
        { "fieldPath": "placa", "order": "ASCENDING" }
      ]
    },
    {
      "collectionGroup": "pagamentos",
      "queryScope": "COLLECTION",
      "fields": [
        { "fieldPath": "mesAno", "order": "ASCENDING" },
        { "fieldPath": "status", "order": "ASCENDING" }
      ]
    },
    {
      "collectionGroup": "pagamentos",
      "queryScope": "COLLECTION",
      "fields": [
        { "fieldPath": "clienteCpf", "order": "ASCENDING" },
        { "fieldPath": "ano", "order": "DESCENDING" },
        { "fieldPath": "mes", "order": "DESCENDING" }
      ]
    }
  ],
  "fieldOverrides": [
    {
      "collectionGroup": "clientes",
      "fieldPath": "cpf",
      "indexes": [
        { "order": "ASCENDING", "queryScope": "COLLECTION" }
      ]
    },
    {
      "collectionGroup": "veiculos",
      "fieldPath": "placa",
      "indexes": [
        { "order": "ASCENDING", "queryScope": "COLLECTION" }
      ]
    },
    {
      "collectionGroup": "veiculos",
      "fieldPath": "imei",
      "indexes": [
        { "order": "ASCENDING", "queryScope": "COLLECTION" }
      ]
    },
    {
      "collectionGroup": "pagamentos",
      "fieldPath": "mesAno",
      "indexes": [
        { "order": "ASCENDING", "queryScope": "COLLECTION" }
      ]
    }
  ]
}
